pychunk/__init__.py
pychunk/chunkers/__init__.py
pychunk/chunkers/base.py
pychunk/chunkers/python_chunker.py
pychunk/nodes/__init__.py
pychunk/nodes/base.py
pychunk/nodes/nodes.py
pychunk/nodes/types.py
pychunk/parser/__init__.py
pychunk/parser/langchain_parser.py
pychunk/parser/llama_index_parser.py
pychunk/utils/__init__.py
pychunk/utils/files_handler.py
pychunk/utils/nodes_utils.py
rag_pychunk-1.1.0.data/scripts/classify-python-code.sh
rag_pychunk-1.1.0.data/scripts/find-node-relationships.sh
rag_pychunk-1.1.0.data/scripts/generate-node-metadata.sh
rag_pychunk-1.1.0.dist-info/LICENSE
rag_pychunk-1.1.0.dist-info/METADATA
rag_pychunk-1.1.0.dist-info/WHEEL
rag_pychunk-1.1.0.dist-info/top_level.txt
rag_pychunk-1.1.0.dist-info/RECORD
