Metadata-Version: 2.1
Name: rag-pychunk
Version: 1.1.0
Summary: Improve your RAG pipelines for your python repositories.
Author: Jaime Sancho Molero
Author-email: jimysanchomolero@gmail.com
License-File: LICENSE
